{"cameraMode":{"drawMode":2,"name":"Shaded Wireframe","section":"Shading Mode"},"sceneLighting":false,"audioPlay":false,"sceneViewState":{"m_AlwaysRefresh":false,"showFog":true,"showSkybox":false,"showFlares":true,"showImageEffects":true,"showParticleSystems":true,"showVisualEffectGraphs":true,"m_FxEnabled":true},"in2DMode":false,"pivot":{"x":535.5481567382813,"y":210.99241638183595,"z":187.001708984375},"rotation":{"x":0.023089541122317315,"y":0.22339549660682679,"z":0.0052924915216863159,"w":-0.9744507670402527},"size":10.0,"orthographic":false}